RSFlib/CalcFunctions.py
RSFlib/ColorSearch.py
RSFlib/Constants.py
RSFlib/DataManagement.py
RSFlib/TkinterExtension.py
RSFlib/__init__.py
RSFlib/pylipsometry.py
RSFlib/opt_data/Sb3O2_FL_fit.rsfile
RSFlib/opt_data/__init__.py
RSFlib/opt_data/al2o3.rsfile
RSFlib/opt_data/si_jaw2.rsfile
RSFlib/opt_data/sio2_fmetrix.rsfile
RSFlib/opt_data/sio2_jaw2.rsfile
RSFlib-0.2.4.dist-info/METADATA
RSFlib-0.2.4.dist-info/WHEEL
RSFlib-0.2.4.dist-info/top_level.txt
RSFlib-0.2.4.dist-info/RECORD
