Metadata-Version: 2.1
Name: RSFlib
Version: 0.2.4
Summary: Useful functions and constants for Fyzing struggle
Author: Radzym (Radim Slovák)
Author-email: <slovak.radim@seznam.cz>
Keywords: python,data analysis,physics,ellipsometry
Classifier: Development Status :: 4 - Beta
Classifier: Intended Audience :: Developers
Classifier: Programming Language :: Python :: 3
Classifier: Operating System :: Unix
Classifier: Operating System :: MacOS :: MacOS X
Classifier: Operating System :: Microsoft :: Windows
Requires-Dist: pandas
